taiga_contrib_ldap_auth_enhanced/__init__.py
taiga_contrib_ldap_auth_enhanced/apps.py
taiga_contrib_ldap_auth_enhanced/connector.py
taiga_contrib_ldap_auth_enhanced/services.py
taiga_contrib_ldap_auth_enhanced-0.6.dist-info/licenses/AUTHORS.md
taiga_contrib_ldap_auth_enhanced-0.6.dist-info/licenses/LICENSE
taiga_contrib_ldap_auth_enhanced-0.6.dist-info/licenses/LICENSE.txt
taiga_contrib_ldap_auth_enhanced-0.6.dist-info/METADATA
taiga_contrib_ldap_auth_enhanced-0.6.dist-info/WHEEL
taiga_contrib_ldap_auth_enhanced-0.6.dist-info/top_level.txt
taiga_contrib_ldap_auth_enhanced-0.6.dist-info/RECORD
