Metadata-Version: 2.4
Name: taiga-contrib-ldap-auth-enhanced
Version: 0.6
Summary: LDAP authentication plugin for self-hosted Taiga.io project management instances
Home-page: https://github.com/TuringTux/taiga-contrib-ldap-auth-enhanced
Author: TuringTux
Author-email: hi@turingtux.me
License: AGPL
Keywords: taiga,ldap,auth,plugin
Classifier: Programming Language :: Python
Classifier: Development Status :: 5 - Production/Stable
Classifier: Framework :: Django
Classifier: Intended Audience :: Developers
Classifier: License :: OSI Approved :: GNU Affero General Public License v3
Classifier: Operating System :: OS Independent
Classifier: Programming Language :: Python
Classifier: Topic :: Internet :: WWW/HTTP
License-File: LICENSE
License-File: LICENSE.txt
License-File: AUTHORS.md
Requires-Dist: django>=1.7
Requires-Dist: ldap3>=0.9.8.4
Dynamic: author
Dynamic: author-email
Dynamic: classifier
Dynamic: description
Dynamic: description-content-type
Dynamic: home-page
Dynamic: keywords
Dynamic: license
Dynamic: license-file
Dynamic: requires-dist
Dynamic: summary
